smapy/__init__.py
smapy/action.py
smapy/api.py
smapy/application.py
smapy/cli.py
smapy/logging_utils.py
smapy/middleware.py
smapy/resource.py
smapy/runnable.py
smapy/utils.py
smapy/actions/__init__.py
smapy/actions/hello.py
smapy/resources/__init__.py
smapy/resources/misc.py
smapy-0.0.3.dist-info/AUTHORS.rst
smapy-0.0.3.dist-info/LICENSE
smapy-0.0.3.dist-info/METADATA
smapy-0.0.3.dist-info/WHEEL
smapy-0.0.3.dist-info/entry_points.txt
smapy-0.0.3.dist-info/top_level.txt
smapy-0.0.3.dist-info/RECORD
